seata/Boostrap.py
seata/__init__.py
seata/boot/GlobalTransactionScanner.py
seata/boot/__init__.py
seata/config/Config.py
seata/config/Configuration.py
seata/config/FileConfig.py
seata/config/NacosConfig.py
seata/config/__init__.py
seata/core/ByteBuffer.py
seata/core/Number.py
seata/core/__init__.py
seata/core/c/Future.py
seata/core/c/__init__.py
seata/core/compressor/CompressorFactory.py
seata/core/compressor/CompressorType.py
seata/core/compressor/DefaultCompressor.py
seata/core/compressor/__init__.py
seata/core/context/ContextCore.py
seata/core/context/RootContext.py
seata/core/context/__init__.py
seata/core/model/BranchStatus.py
seata/core/model/BranchType.py
seata/core/model/GlobalStatus.py
seata/core/model/__init__.py
seata/core/protocol/AbstractIdentifyRequestResponseCodec.py
seata/core/protocol/AbstractResultMessageCodec.py
seata/core/protocol/HeartbeatMessage.py
seata/core/protocol/MergeResultMessage.py
seata/core/protocol/MergeResultMessageCodec.py
seata/core/protocol/MergedWarpMessage.py
seata/core/protocol/MergedWarpMessageCodec.py
seata/core/protocol/MessageType.py
seata/core/protocol/MessageTypeAware.py
seata/core/protocol/ProtocolConstants.py
seata/core/protocol/RegisterRMRequestResponse.py
seata/core/protocol/RegisterRMRequestResponseCodec.py
seata/core/protocol/RegisterTMRequestResponse.py
seata/core/protocol/RegisterTMRequestResponseCodec.py
seata/core/protocol/ResultCode.py
seata/core/protocol/RpcMessage.py
seata/core/protocol/Version.py
seata/core/protocol/__init__.py
seata/core/protocol/transaction/AbstractBranchEndRequestResponseCodec.py
seata/core/protocol/transaction/AbstractGlobalEndRequestResponseCodec.py
seata/core/protocol/transaction/AbstractTransactionRequestResponseCodec.py
seata/core/protocol/transaction/BranchCommitRequestResponse.py
seata/core/protocol/transaction/BranchCommitRequestResponseCodec.py
seata/core/protocol/transaction/BranchRegisterRequestResponse.py
seata/core/protocol/transaction/BranchRegisterRequestResponseCodec.py
seata_python-0.1.dist-info/LICENSE
seata_python-0.1.dist-info/METADATA
seata_python-0.1.dist-info/WHEEL
seata_python-0.1.dist-info/top_level.txt
seata_python-0.1.dist-info/RECORD
