Metadata-Version: 2.1
Name: seata-python
Version: 0.1
Summary: seata-python
Home-page: https://github.com/opentrx/seata-python
Author: jsbxyyx
Author-email: jsbxyyx@163.com
License: Apache License 2.0
Platform: UNKNOWN
Classifier: Programming Language :: Python :: 3.7
Classifier: Operating System :: OS Independent
Requires-Python: >=3.7
Requires-Dist: DBUtils (==2.0)
Requires-Dist: antlr4-mysql (==0.1.1)
Requires-Dist: protobuf (==3.17.3)
Requires-Dist: PyYAML (==5.4.1)
Requires-Dist: loguru (==0.5.3)
